hqsbase/__init__.py
hqsbase/__version__.py
hqsbase/calculator/__init__.py
hqsbase/calculator/calculator.py
hqsbase/qonfig/__init__.py
hqsbase/qonfig/qonfig.py
hqsbase/qonfig/qonfig_helper_classes.py
hqsbase-0.7.9.dist-info/LICENSE
hqsbase-0.7.9.dist-info/METADATA
hqsbase-0.7.9.dist-info/WHEEL
hqsbase-0.7.9.dist-info/top_level.txt
hqsbase-0.7.9.dist-info/RECORD
