Metadata-Version: 2.1
Name: hqsbase
Version: 0.7.9
Summary: HQS base utility package
Home-page: https://quantumsimulations.de
Author: HQS Quantum Simulations GmbH
Author-email: info@quantumsimulations.de
License: Apache-2.0
Platform: UNKNOWN
Requires-Dist: h5py
Requires-Dist: pandas
Requires-Dist: pytest
Requires-Dist: tables
Requires-Dist: pyyaml
Requires-Dist: qoqo-calculator-pyo3 (>=0.1.5)
